hacknehs/__init__.py
hacknehs-0.0.1.dist-info/LICENSE
hacknehs-0.0.1.dist-info/METADATA
hacknehs-0.0.1.dist-info/WHEEL
hacknehs-0.0.1.dist-info/top_level.txt
hacknehs-0.0.1.dist-info/RECORD
