Metadata-Version: 2.1
Name: hacknehs
Version: 0.0.1
Summary: An elegant way to get to hacknehs.org faster!
Home-page: https://github.com/jeffreyzpan/hacknehs
Author: Jeffrey Pan
Author-email: info@hacknehs.org
License: UNKNOWN
Platform: UNKNOWN
Classifier: Programming Language :: Python :: 3
Classifier: License :: OSI Approved :: MIT License
Classifier: Operating System :: OS Independent
Requires-Python: >=3.6
